label_sorter/__init__.py
label_sorter/core.py
label_sorter/platforms/__init__.py
label_sorter/platforms/ecommerce/__init__.py
label_sorter/platforms/ecommerce/amazon.py
label_sorter/platforms/ecommerce/amazon.sync-conflict-20251219-112347-UX2O7G6.py
label_sorter/platforms/ecommerce/base_label.py
label_sorter/platforms/ecommerce/base_label.sync-conflict-20251219-112348-UX2O7G6.py
label_sorter/platforms/ecommerce/shopify.py
label_sorter/platforms/ecommerce/shopify.sync-conflict-20251219-112348-UX2O7G6.py
label_sorter-0.5.dist-info/licenses/LICENSE
label_sorter-0.5.dist-info/METADATA
label_sorter-0.5.dist-info/WHEEL
label_sorter-0.5.dist-info/top_level.txt
label_sorter-0.5.dist-info/RECORD
