Metadata-Version: 2.4
Name: label_sorter
Version: 0.5
Summary: Library to sort Amazon and Shopify shipping labels
Author-email: Harry19967 <harilalsunil2@gmail.com>
License-Expression: MIT
Project-URL: Homepage, https://github.com/harilal766/Ecommerce-label-sorter
Project-URL: Issues, https://github.com/harilal766/Ecommerce-label-sorter/issues
Classifier: Programming Language :: Python :: 3
Classifier: Operating System :: OS Independent
Requires-Python: >=3.9
License-File: LICENSE
Dynamic: license-file
